{"metadata": {"dbt_schema_version": "https://schemas.getdbt.com/dbt/run-results/v6.json", "dbt_version": "1.10.22", "generated_at": "2026-06-09T17:24:32.814915Z", "invocation_id": "739b638c-042b-48e7-82e6-b9cef8ab253c", "invocation_started_at": "2026-06-09T17:24:23.303727Z", "env": {}}, "results": [{"status": "pass", "timing": [{"name": "compile", "started_at": "2026-06-09T17:24:31.533325Z", "completed_at": "2026-06-09T17:24:31.589706Z"}, {"name": "execute", "started_at": "2026-06-09T17:24:31.592929Z", "completed_at": "2026-06-09T17:24:31.731307Z"}], "thread_id": "Thread-1 (worker)", "execution_time": 0.21520662307739258, "adapter_response": {"_message": "OK"}, "message": null, "failures": 0, "unique_id": "test.sales_dbt.accepted_values_fct_customer_metrics_rfm_segment__Champions__Loyal__Recent__At_Risk__Regular.c5e9bd0cd6", "compiled": true, "compiled_code": "\n    \n    \n\nwith all_values as (\n\n    select\n        rfm_segment as value_field,\n        count(*) as n_records\n\n    from \"retail_analytics\".\"analytics\".\"fct_customer_metrics\"\n    group by rfm_segment\n\n)\n\nselect *\nfrom all_values\nwhere value_field not in (\n    'Champions','Loyal','Recent','At Risk','Regular'\n)\n\n\n", "relation_name": null, "batch_results": null}, {"status": "pass", "timing": [{"name": "compile", "started_at": "2026-06-09T17:24:31.761982Z", "completed_at": "2026-06-09T17:24:31.785585Z"}, {"name": "execute", "started_at": "2026-06-09T17:24:31.787584Z", "completed_at": "2026-06-09T17:24:31.920136Z"}], "thread_id": "Thread-1 (worker)", "execution_time": 0.17035388946533203, "adapter_response": {"_message": "OK"}, "message": null, "failures": 0, "unique_id": "test.sales_dbt.dbt_utils_accepted_range_stg_orders_total_quantity__0.07f7dc0d38", "compiled": true, "compiled_code": "\n\nwith meet_condition as(\n  select *\n  from \"retail_analytics\".\"analytics\".\"stg_orders\"\n),\n\nvalidation_errors as (\n  select *\n  from meet_condition\n  where\n    -- never true, defaults to an empty result set. Exists to ensure any combo of the `or` clauses below succeeds\n    1 = 2\n    -- records with a value >= min_value are permitted. The `not` flips this to find records that don't meet the rule.\n    or not total_quantity >= 0\n)\n\nselect *\nfrom validation_errors\n\n", "relation_name": null, "batch_results": null}, {"status": "pass", "timing": [{"name": "compile", "started_at": "2026-06-09T17:24:31.941544Z", "completed_at": "2026-06-09T17:24:31.954943Z"}, {"name": "execute", "started_at": "2026-06-09T17:24:31.957940Z", "completed_at": "2026-06-09T17:24:31.993553Z"}], "thread_id": "Thread-1 (worker)", "execution_time": 0.0651998519897461, "adapter_response": {"_message": "OK"}, "message": null, "failures": 0, "unique_id": "test.sales_dbt.dbt_utils_expression_is_true_fct_daily_sales_daily_revenue_0.1ab209999f", "compiled": true, "compiled_code": "\n\n\n\nselect\n    1\nfrom \"retail_analytics\".\"analytics\".\"fct_daily_sales\"\n\nwhere not(daily_revenue >= 0)\n\n", "relation_name": null, "batch_results": null}, {"status": "pass", "timing": [{"name": "compile", "started_at": "2026-06-09T17:24:32.019190Z", "completed_at": "2026-06-09T17:24:32.048811Z"}, {"name": "execute", "started_at": "2026-06-09T17:24:32.051809Z", "completed_at": "2026-06-09T17:24:32.094416Z"}], "thread_id": "Thread-1 (worker)", "execution_time": 0.09244751930236816, "adapter_response": {"_message": "OK"}, "message": null, "failures": 0, "unique_id": "test.sales_dbt.not_null_fct_customer_metrics_customer_id.ab9639bfe5", "compiled": true, "compiled_code": "\n    \n    \n\n\n\nselect customer_id\nfrom \"retail_analytics\".\"analytics\".\"fct_customer_metrics\"\nwhere customer_id is null\n\n\n", "relation_name": null, "batch_results": null}, {"status": "pass", "timing": [{"name": "compile", "started_at": "2026-06-09T17:24:32.128091Z", "completed_at": "2026-06-09T17:24:32.148513Z"}, {"name": "execute", "started_at": "2026-06-09T17:24:32.151509Z", "completed_at": "2026-06-09T17:24:32.187368Z"}], "thread_id": "Thread-1 (worker)", "execution_time": 0.0747063159942627, "adapter_response": {"_message": "OK"}, "message": null, "failures": 0, "unique_id": "test.sales_dbt.not_null_fct_daily_sales_daily_revenue.05b96edfb2", "compiled": true, "compiled_code": "\n    \n    \n\n\n\nselect daily_revenue\nfrom \"retail_analytics\".\"analytics\".\"fct_daily_sales\"\nwhere daily_revenue is null\n\n\n", "relation_name": null, "batch_results": null}, {"status": "pass", "timing": [{"name": "compile", "started_at": "2026-06-09T17:24:32.212793Z", "completed_at": "2026-06-09T17:24:32.242993Z"}, {"name": "execute", "started_at": "2026-06-09T17:24:32.245196Z", "completed_at": "2026-06-09T17:24:32.288092Z"}], "thread_id": "Thread-1 (worker)", "execution_time": 0.08950328826904297, "adapter_response": {"_message": "OK"}, "message": null, "failures": 0, "unique_id": "test.sales_dbt.not_null_stg_orders_order_id.81cfe2fe64", "compiled": true, "compiled_code": "\n    \n    \n\n\n\nselect order_id\nfrom \"retail_analytics\".\"analytics\".\"stg_orders\"\nwhere order_id is null\n\n\n", "relation_name": null, "batch_results": null}, {"status": "pass", "timing": [{"name": "compile", "started_at": "2026-06-09T17:24:32.312500Z", "completed_at": "2026-06-09T17:24:32.333116Z"}, {"name": "execute", "started_at": "2026-06-09T17:24:32.335116Z", "completed_at": "2026-06-09T17:24:32.434741Z"}], "thread_id": "Thread-1 (worker)", "execution_time": 0.13546538352966309, "adapter_response": {"_message": "OK"}, "message": null, "failures": 0, "unique_id": "test.sales_dbt.not_null_stg_orders_order_revenue.05ba9d7e08", "compiled": true, "compiled_code": "\n    \n    \n\n\n\nselect order_revenue\nfrom \"retail_analytics\".\"analytics\".\"stg_orders\"\nwhere order_revenue is null\n\n\n", "relation_name": null, "batch_results": null}, {"status": "pass", "timing": [{"name": "compile", "started_at": "2026-06-09T17:24:32.459180Z", "completed_at": "2026-06-09T17:24:32.475603Z"}, {"name": "execute", "started_at": "2026-06-09T17:24:32.477604Z", "completed_at": "2026-06-09T17:24:32.513880Z"}], "thread_id": "Thread-1 (worker)", "execution_time": 0.06891322135925293, "adapter_response": {"_message": "OK"}, "message": null, "failures": 0, "unique_id": "test.sales_dbt.source_not_null_raw_online_retail_raw_InvoiceNo.3893ac3704", "compiled": true, "compiled_code": "\n    \n    \n\n\n\nselect InvoiceNo\nfrom \"retail_analytics\".\"raw\".\"online_retail_raw\"\nwhere InvoiceNo is null\n\n\n", "relation_name": null, "batch_results": null}, {"status": "pass", "timing": [{"name": "compile", "started_at": "2026-06-09T17:24:32.540358Z", "completed_at": "2026-06-09T17:24:32.564971Z"}, {"name": "execute", "started_at": "2026-06-09T17:24:32.566971Z", "completed_at": "2026-06-09T17:24:32.601590Z"}], "thread_id": "Thread-1 (worker)", "execution_time": 0.07648420333862305, "adapter_response": {"_message": "OK"}, "message": null, "failures": 0, "unique_id": "test.sales_dbt.source_not_null_raw_online_retail_raw_Revenue.77e761eeed", "compiled": true, "compiled_code": "\n    \n    \n\n\n\nselect Revenue\nfrom \"retail_analytics\".\"raw\".\"online_retail_raw\"\nwhere Revenue is null\n\n\n", "relation_name": null, "batch_results": null}, {"status": "pass", "timing": [{"name": "compile", "started_at": "2026-06-09T17:24:32.626247Z", "completed_at": "2026-06-09T17:24:32.659888Z"}, {"name": "execute", "started_at": "2026-06-09T17:24:32.661888Z", "completed_at": "2026-06-09T17:24:32.766702Z"}], "thread_id": "Thread-1 (worker)", "execution_time": 0.15689444541931152, "adapter_response": {"_message": "OK"}, "message": null, "failures": 0, "unique_id": "test.sales_dbt.unique_stg_orders_order_id.e3b841c71a", "compiled": true, "compiled_code": "\n    \n    \n\nselect\n    order_id as unique_field,\n    count(*) as n_records\n\nfrom \"retail_analytics\".\"analytics\".\"stg_orders\"\nwhere order_id is not null\ngroup by order_id\nhaving count(*) > 1\n\n\n", "relation_name": null, "batch_results": null}], "elapsed_time": 1.6785764694213867, "args": {"print": true, "show_all_deprecations": false, "log_level": "info", "log_file_max_bytes": 10485760, "source_freshness_run_project_hooks": true, "strict_mode": false, "require_yaml_configuration_for_mf_time_spines": false, "use_fast_test_edges": false, "partial_parse": true, "select": [], "state_modified_compare_vars": false, "which": "test", "show_resource_report": false, "validate_macro_args": false, "log_format_file": "debug", "log_format": "default", "exclude": [], "require_all_warnings_handled_by_warn_error": false, "indirect_selection": "eager", "introspect": true, "printer_width": 80, "skip_nodes_if_on_run_start_fails": false, "require_resource_names_without_spaces": true, "use_colors": true, "warn_error_options": {"error": [], "warn": [], "silence": []}, "populate_cache": true, "cache_selected_only": false, "quiet": false, "profiles_dir": "C:\\Users\\Aleksei\\Desktop\\Portfolio\\1. ETL\\sales-etl-pipeline\\sales_dbt", "send_anonymous_usage_stats": true, "log_level_file": "debug", "exclude_resource_types": [], "partial_parse_file_diff": true, "upload_to_artifacts_ingest_api": false, "defer": false, "state_modified_compare_more_unrendered_values": false, "require_explicit_package_overrides_for_builtin_materializations": true, "use_colors_file": true, "macro_debugging": false, "version_check": true, "resource_types": [], "require_generic_test_arguments_property": true, "static_parser": true, "vars": {}, "write_json": true, "require_batched_execution_for_custom_microbatch_strategy": false, "project_dir": "C:\\Users\\Aleksei\\Desktop\\Portfolio\\1. ETL\\sales-etl-pipeline\\sales_dbt", "favor_state": false, "require_nested_cumulative_type_params": false, "log_path": "C:\\Users\\Aleksei\\Desktop\\Portfolio\\1. ETL\\sales-etl-pipeline\\sales_dbt\\logs", "invocation_command": "dbt test"}}